quantastica_encoder_decoder-0.1.1-py3.11-nspkg.pth
quantastica/encoder_decoder/__init__.py
quantastica/encoder_decoder/encoder_decoder.py
quantastica_encoder_decoder-0.1.1.dist-info/LICENSE
quantastica_encoder_decoder-0.1.1.dist-info/METADATA
quantastica_encoder_decoder-0.1.1.dist-info/WHEEL
quantastica_encoder_decoder-0.1.1.dist-info/namespace_packages.txt
quantastica_encoder_decoder-0.1.1.dist-info/top_level.txt
quantastica_encoder_decoder-0.1.1.dist-info/RECORD
