Metadata-Version: 2.1
Name: quantastica-encoder-decoder
Version: 0.1.1
Summary: Helper library for encoding classical data into quantum state and vice versa
Home-page: https://github.com/quantastica/encoder-decoder
Author: Quantastica
Author-email: support@quantastica.com
License: Apache License 2.0
Classifier: Development Status :: 4 - Beta
Classifier: License :: OSI Approved :: Apache Software License
Classifier: Programming Language :: Python :: 3
Classifier: Intended Audience :: Science/Research
License-File: LICENSE
